README.md
setup.py
pulumi_sonarr/__init__.py
pulumi_sonarr/_inputs.py
pulumi_sonarr/_utilities.py
pulumi_sonarr/provider.py
pulumi_sonarr/pulumi-plugin.json
pulumi_sonarr/py.typed
pulumi_sonarr.egg-info/PKG-INFO
pulumi_sonarr.egg-info/SOURCES.txt
pulumi_sonarr.egg-info/dependency_links.txt
pulumi_sonarr.egg-info/not-zip-safe
pulumi_sonarr.egg-info/requires.txt
pulumi_sonarr.egg-info/top_level.txt
pulumi_sonarr/config/__init__.py
pulumi_sonarr/config/outputs.py
pulumi_sonarr/config/vars.py
pulumi_sonarr/downloadclients/__init__.py
pulumi_sonarr/downloadclients/aria2.py
pulumi_sonarr/downloadclients/config.py
pulumi_sonarr/downloadclients/deluge.py
pulumi_sonarr/downloadclients/download_client.py
pulumi_sonarr/downloadclients/flood.py
pulumi_sonarr/downloadclients/get_config.py
pulumi_sonarr/downloadclients/get_download_client.py
pulumi_sonarr/downloadclients/get_download_clients.py
pulumi_sonarr/downloadclients/get_remote_path_mapping.py
pulumi_sonarr/downloadclients/get_remote_path_mappings.py
pulumi_sonarr/downloadclients/hadouken.py
pulumi_sonarr/downloadclients/nzbget.py
pulumi_sonarr/downloadclients/nzbvortex.py
pulumi_sonarr/downloadclients/outputs.py
pulumi_sonarr/downloadclients/pneumatic.py
pulumi_sonarr/downloadclients/qbittorrent.py
pulumi_sonarr/downloadclients/remote_path_mapping.py
pulumi_sonarr/downloadclients/rtorrent.py
pulumi_sonarr/downloadclients/sabnzbd.py
pulumi_sonarr/downloadclients/torrent_blackhole.py
pulumi_sonarr/downloadclients/torrent_download_station.py
pulumi_sonarr/downloadclients/transmission.py
pulumi_sonarr/downloadclients/usenet_blackhole.py
pulumi_sonarr/downloadclients/usenet_download_station.py
pulumi_sonarr/downloadclients/utorrent.py
pulumi_sonarr/downloadclients/vuze.py
pulumi_sonarr/importlists/__init__.py
pulumi_sonarr/importlists/custom.py
pulumi_sonarr/importlists/exclusion.py
pulumi_sonarr/importlists/get_exclusion.py
pulumi_sonarr/importlists/get_exclusions.py
pulumi_sonarr/importlists/get_import_list.py
pulumi_sonarr/importlists/get_import_lists.py
pulumi_sonarr/importlists/imdb.py
pulumi_sonarr/importlists/import_list.py
pulumi_sonarr/importlists/outputs.py
pulumi_sonarr/importlists/plex.py
pulumi_sonarr/importlists/plex_rss.py
