Metadata-Version: 2.1
Name: pulumi-sonarr
Version: 4.0.0a2
Summary: A Pulumi package for creating and managing Sonarr resources
Home-page: https://github.com/MaienM/pulumi-sonarr
License: Apache-2.0
Project-URL: Repository, https://github.com/MaienM/pulumi-sonarr
Keywords: pulumi sonarr category/utility
Requires-Python: >=3.7
